{"sections":{"rich_text_ERtJkq":{"type":"rich-text","blocks":{"heading_6br7eJ":{"type":"heading","settings":{"heading":"Welcome To Prime Pickz!","heading_size":"h1"}},"text_8Mgcy6":{"type":"text","settings":{"text":"<h3><strong>30% OFF Storewide<\/strong> 'Til  Sunday! Don't Miss Out!<\/h3>"}},"button_9TRW7w":{"type":"button","settings":{"button_label":"Shop All","button_link":"shopify:\/\/collections\/all","button_style_secondary":false,"button_label_2":"","button_link_2":"","button_style_secondary_2":false}}},"block_order":["heading_6br7eJ","text_8Mgcy6","button_9TRW7w"],"settings":{"desktop_content_position":"center","content_alignment":"center","color_scheme":"scheme-1","full_width":true,"padding_top":8,"padding_bottom":8}},"featured_collection_iCCmpx":{"type":"featured-collection","settings":{"collection":"products-with-orders-09-24-2024","products_to_show":10,"title":"You Might Like These!","heading_size":"h2","description":"","show_description":false,"description_style":"body","columns_desktop":4,"enable_desktop_slider":false,"full_width":false,"show_view_all":false,"view_all_style":"solid","color_scheme":"scheme-1","image_ratio":"square","image_shape":"default","show_secondary_image":true,"show_vendor":false,"show_rating":false,"quick_add":"none","columns_mobile":"2","swipe_on_mobile":false,"padding_top":8,"padding_bottom":8}}},"order":["rich_text_ERtJkq","featured_collection_iCCmpx"]}